mpl_font/__init__.py
mpl_font/msyh.py
mpl_font/noto.py
mpl_font/wqy.py
mpl_font/fonts/noto/NotoSansCJKsc-Bold.otf
mpl_font/fonts/noto/NotoSansCJKsc-Light.otf
mpl_font/fonts/noto/NotoSansCJKsc-Medium.otf
mpl_font/fonts/noto/NotoSansCJKsc-Regular.otf
mpl_font/fonts/wqy/wqy-microhei.ttc
tests/__init__.py
tests/fonts.py
mpl_font-1.1.0.dist-info/METADATA
mpl_font-1.1.0.dist-info/WHEEL
mpl_font-1.1.0.dist-info/top_level.txt
mpl_font-1.1.0.dist-info/RECORD
