Metadata-Version: 2.1
Name: mpl-font
Version: 1.1.0
Summary: CJK font selector for matplotlib
Home-page: https://github.com/koho/mpl-font
Author: Gerhard Tan
Author-email: gwohau.tan@gmail.com
License: BSD
Platform: any
Requires-Dist: matplotlib (>=3.2.0)
